cgmetadata/__init__.py
cgmetadata/__main__.py
cgmetadata/_version.py
cgmetadata/cgmetadata.py
cgmetadata/classes.py
cgmetadata/cli.py
cgmetadata/constants.py
cgmetadata/iso6709.py
cgmetadata/metadata.py
cgmetadata/types.py
cgmetadata/utils.py
cgmetadata/xmp.py
cgmetadata-0.1.6.dist-info/entry_points.txt
cgmetadata-0.1.6.dist-info/LICENSE
cgmetadata-0.1.6.dist-info/WHEEL
cgmetadata-0.1.6.dist-info/METADATA
cgmetadata-0.1.6.dist-info/RECORD
