Metadata-Version: 2.1
Name: cgmetadata
Version: 0.1.6
Summary: Use native Core Graphics / ImageIO API on macOS to access and change image metadata
Author-email: Rhet Turnbull <rturnbull+git@gmail.com>
Requires-Python: >3.9
Classifier: License :: OSI Approved :: MIT License
Requires-Dist: pyobjc-core>=9.2
Requires-Dist: pyobjc-framework-AVFoundation>=9.2
Requires-Dist: pyobjc-framework-CoreLocation>=9.2
Requires-Dist: pyobjc-framework-Quartz>=9.2
Requires-Dist: pyobjc-framework-UniformTypeIdentifiers>=9.2
Requires-Dist: rich>=13.0.0
Requires-Dist: wheel>=0.41.2
Requires-Dist: wurlitzer>=3.0.3
Requires-Dist: bump2version==1.0.1 ; extra == "dev"
Requires-Dist: mkdocs>=1.4.2 ; extra == "docs"
Requires-Dist: mkdocs-material>=9.0.13 ; extra == "docs"
Requires-Dist: mkdocstrings-python>=0.8.3 ; extra == "docs"
Requires-Dist: pytest>=7.4.2 ; extra == "test"
Requires-Dist: pytest-cov ; extra == "test"
Requires-Dist: mypy>=1.6.1 ; extra == "test"
Project-URL: Home, https://github.com/RhetTbull/cgmetadata
Project-URL: Issues, https://github.com/RhetTbull/cgmetadata/issues
Project-URL: Source, https://github.com/RhetTbull/cgmetadata
Provides-Extra: dev
Provides-Extra: docs
Provides-Extra: test
